接口请求时间：2018-07-11 17:07:40→→→→→<ROOT><RETURN_CODE>0</RETURN_CODE><RETURN_MSG>查询对账信息成功</RETURN_MSG><RES><COUNT>69</COUNT><ACCOUNT_LIST><ORDER_ID>201807102909725542</ORDER_ID><HOSP_ORDER_ID>WY201807102909725542</HOSP_ORDER_ID><ORDER_TYPE>1</ORDER_TYPE><AUDIT_STATUS>2</AUDIT_STATUS><HOSP_TRADE_ID>9718632</HOSP_TRADE_ID><PAY_CHANNEL_ID>1</PAY_CHANNEL_ID><SERIAL_NUM>2018071023592725406100000002</SERIAL_NUM><PAY_FEE>1930</PAY_FEE><PAY_DATETIME>2018-07-10 23:59:33</PAY_DATETIME><HOSP_PATIENT_ID>0006042232</HOSP_PATIENT_ID><NAME>郭庆</NAME><CERT_NO>43098119921001002X</CERT_NO></ACCOUNT_LIST><ACCOUNT_LIST><ORDER_ID>201807102908092046</ORDER_ID><HOSP_ORDER_ID>WY201807102908092046</HOSP_ORDER_ID><ORDER_TYPE>1</ORDER_TYPE><AUDIT_STATUS>2</AUDIT_STATUS><HOSP_TRADE_ID>9718587</HOSP_TRADE_ID><PAY_CHANNEL_ID>1</PAY_CHANNEL_ID><SERIAL_NUM>2018071023225387700800000002</SERIAL_NUM><PAY_FEE>1930</PAY_FEE><PAY_DATETIME>2018-07-10 23:24:41</PAY_DATETIME><HOSP_PATIENT_ID>0005735630</HOSP_PATIENT_ID><NAME>吴清香</NAME><CERT_NO>460004199107051425</CERT_NO></ACCOUNT_LIST><ACCOUNT_LIST><ORDER_ID>201807102909611032</ORDER_ID><HOSP_ORDER_ID>WY201807102909611032</HOSP_ORDER_ID><ORDER_TYPE>1</ORDER_TYPE><AUDIT_STATUS>2</AUDIT_STATUS><HOSP_TRADE_ID>9718570</HOSP_TRADE_ID><PAY_CHANNEL_ID>1</PAY_CHANNEL_ID><SERIAL_NUM>2018071023141405906100000002</SERIAL_NUM><PAY_FEE>1530</PAY_FEE><PAY_DATETIME>2018-07-10 23:14:22</PAY_DATETIME><HOSP_PATIENT_ID>0005868009</HOSP_PATIENT_ID><NAME>毛惠琪</NAME><CERT_NO>460103199009160029</CERT_NO></ACCOUNT_LIST><ACCOUNT_LIST><ORDER_ID>201807102909597340</ORDER_ID><HOSP_ORDER_ID>WY201807102909597340</HOSP_ORDER_ID><ORDER_TYPE>1</ORDER_TYPE><AUDIT_STATUS>2</AUDIT_STATUS><HOSP_TRADE_ID>9718546</HOSP_TRADE_ID><PAY_CHANNEL_ID>1</PAY_CHANNEL_ID><SERIAL_NUM>2018071023013025706000000003</SERIAL_NUM><PAY_FEE>1930</PAY_FEE><PAY_DATETIME>2018-07-10 23:01:39</PAY_DATETIME><HOSP_PATIENT_ID>0005816200</HOSP_PATIENT_ID><NAME>陈伟翔</NAME><CERT_NO>46902420140330083X</CERT_NO></ACCOUNT_LIST><ACCOUNT_LIST><ORDER_ID>201807102907702173</ORDER_ID><HOSP_ORDER_ID>WY201807102907702173</HOSP_ORDER_ID><ORDER_TYPE>2</ORDER_TYPE><AUDIT_STATUS>2</AUDIT_STATUS><HOSP_TRADE_ID>573474@0005816200</HOSP_TRADE_ID><PAY_CHANNEL_ID>1</PAY_CHANNEL_ID><SERIAL_NUM>7472143</SERIAL_NUM><PAY_FEE>1930</PAY_FEE><PAY_DATETIME>2018-07-10 23:00:31</PAY_DATETIME><OLD_HOSP_TRADE_ID>9718052</OLD_HOSP_TRADE_ID><OLD_SERIAL_NUM>2018071018131507006100000001</OLD_SERIAL_NUM><HOSP_PATIENT_ID>0005816200</HOSP_PATIENT_ID><NAME>陈伟翔</NAME><CERT_NO>46902420140330083X</CERT_NO></ACCOUNT_LIST><ACCOUNT_LIST><ORDER_ID>201807102909523978</ORDER_ID><HOSP_ORDER_ID>WY201807102909523978</HOSP_ORDER_ID><ORDER_TYPE>1</ORDER_TYPE><AUDIT_STATUS>2</AUDIT_STATUS><HOSP_TRADE_ID>9718514</HOSP_TRADE_ID><PAY_CHANNEL_ID>1</PAY_CHANNEL_ID><SERIAL_NUM>2018071022493735506100000006</SERIAL_NUM><PAY_FEE>1330</PAY_FEE><PAY_DATETIME>2018-07-10 22:49:46</PAY_DATETIME><HOSP_PATIENT_ID>0006049131</HOSP_PATIENT_ID><NAME>丁慎山</NAME><CERT_NO>370305198107201215</CERT_NO></ACCOUNT_LIST><ACCOUNT_LIST><ORDER_ID>201807102909359047</ORDER_ID><HOSP_ORDER_ID>WY201807102909359047</HOSP_ORDER_ID><ORDER_TYPE>1</ORDER_TYPE><AUDIT_STATUS>2</AUDIT_STATUS><HOSP_TRADE_ID>9718457</HOSP_TRADE_ID><PAY_CHANNEL_ID>1</PAY_CHANNEL_ID><SERIAL_NUM>2018071022153108806100000002</SERIAL_NUM><PAY_FEE>1930</PAY_FEE><PAY_DATETIME>2018-07-10 22:15:44</PAY_DATETIME><HOSP_PATIENT_ID>0006049097</HOSP_PATIENT_ID><NAME>钟盼娜</NAME><CERT_NO>469003200812303226</CERT_NO></ACCOUNT_LIST><ACCOUNT_LIST><ORDER_ID>201807102909313568</ORDER_ID><HOSP_ORDER_ID>WY201807102909313568</HOSP_ORDER_ID><ORDER_TYPE>1</ORDER_TYPE><AUDIT_STATUS>2</AUDIT_STATUS><HOSP_TRADE_ID>9718451</HOSP_TRADE_ID><PAY_CHANNEL_ID>11</PAY_CHANNEL_ID><SERIAL_NUM>2018071022120636706000000001</SERIAL_NUM><PAY_FEE>1930</PAY_FEE><PAY_DATETIME>2018-07-10 22:12:23</PAY_DATETIME><HOSP_PATIENT_ID>0004256953</HOSP_PATIENT_ID><NAME>吴雄</NAME><CERT_NO>46000419790120141X</CERT_NO></ACCOUNT_LIST><ACCOUNT_LIST><ORDER_ID>201807102906589276</ORDER_ID><HOSP_ORDER_ID>WY201807102906589276</HOSP_ORDER_ID><ORDER_TYPE>1</ORDER_TYPE><AUDIT_STATUS>2</AUDIT_STATUS><HOSP_TRADE_ID>9718407</HOSP_TRADE_ID><PAY_CHANNEL_ID>1</PAY_CHANNEL_ID><SERIAL_NUM>2018071021450148900900000001</SERIAL_NUM><PAY_FEE>1530</PAY_FEE><PAY_DATETIME>2018-07-10 21:45:12</PAY_DATETIME><HOSP_PATIENT_ID>0006042281</HOSP_PATIENT_ID><NAME>羊彩鸾</NAME><CERT_NO>460003200005043423</CERT_NO></ACCOUNT_LIST><ACCOUNT_LIST><ORDER_ID>201807102909173820</ORDER_ID><HOSP_ORDER_ID>WY201807102909173820</HOSP_ORDER_ID><ORDER_TYPE>1</ORDER_TYPE><AUDIT_STATUS>2</AUDIT_STATUS><HOSP_TRADE_ID>9718399</HOSP_TRADE_ID><PAY_CHANNEL_ID>1</PAY_CHANNEL_ID><SERIAL_NUM>2018071021402722106000000004</SERIAL_NUM><PAY_FEE>1930</PAY_FEE><PAY_DATETIME>2018-07-10 21:40:37</PAY_DATETIME><HOSP_PATIENT_ID>0006049057</HOSP_PATIENT_ID><NAME>羊带乾</NAME><CERT_NO>460003198708022485</CERT_NO></ACCOUNT_LIST><ACCOUNT_LIST><ORDER_ID>201807102908861165</ORDER_ID><HOSP_ORDER_ID>WY201807102908861165</HOSP_ORDER_ID><ORDER_TYPE>1</ORDER_TYPE><AUDIT_STATUS>2</AUDIT_STATUS><HOSP_TRADE_ID>9718331</HOSP_TRADE_ID><PAY_CHANNEL_ID>1</PAY_CHANNEL_ID><SERIAL_NUM>2018071020565611706000000007</SERIAL_NUM><PAY_FEE>1930</PAY_FEE><PAY_DATETIME>2018-07-10 20:57:13</PAY_DATETIME><HOSP_PATIENT_ID>0006049047</HOSP_PATIENT_ID><NAME>李秋潭</NAME><CERT_NO>469003201301213717</CERT_NO></ACCOUNT_LIST><ACCOUNT_LIST><ORDER_ID>201807102908853953</ORDER_ID><HOSP_ORDER_ID>WY201807102908853953</HOSP_ORDER_ID><ORDER_TYPE>1</ORDER_TYPE><AUDIT_STATUS>2</AUDIT_STATUS><HOSP_TRADE_ID>9718324</HOSP_TRADE_ID><PAY_CHANNEL_ID>1</PAY_CHANNEL_ID><SERIAL_NUM>2018071020530576306100000001</SERIAL_NUM><PAY_FEE>1930</PAY_FEE><PAY_DATETIME>2018-07-10 20:53:18</PAY_DATETIME><HOSP_PATIENT_ID>0006049045</HOSP_PATIENT_ID><NAME>杨晓剑</NAME><CERT_NO>533224197604142318</CERT_NO></ACCOUNT_LIST><ACCOUNT_LIST><ORDER_ID>201807102908734581</ORDER_ID><HOSP_ORDER_ID>WY201807102908734581</HOSP_ORDER_ID><ORDER_TYPE>1</ORDER_TYPE><AUDIT_STATUS>2</AUDIT_STATUS><HOSP_TRADE_ID>9718306</HOSP_TRADE_ID><PAY_CHANNEL_ID>1</PAY_CHANNEL_ID><SERIAL_NUM>2018071020370610506100000002</SERIAL_NUM><PAY_FEE>1930</PAY_FEE><PAY_DATETIME>2018-07-10 20:38:22</PAY_DATETIME><HOSP_PATIENT_ID>0006046962</HOSP_PATIENT_ID><NAME>陆如玲</NAME><CERT_NO>460027197308120680</CERT_NO></ACCOUNT_LIST><ACCOUNT_LIST><ORDER_ID>201807102904939390</ORDER_ID><HOSP_ORDER_ID>WY201807102904939390</HOSP_ORDER_ID><ORDER_TYPE>2</ORDER_TYPE><AUDIT_STATUS>2</AUDIT_STATUS><HOSP_TRADE_ID>574695@0006046962</HOSP_TRADE_ID><PAY_CHANNEL_ID>1</PAY_CHANNEL_ID><SERIAL_NUM>7469734</SERIAL_NUM><PAY_FEE>1530</PAY_FEE><PAY_DATETIME>2018-07-10 20:35:50</PAY_DATETIME><OLD_HOSP_TRADE_ID>9716719</OLD_HOSP_TRADE_ID><OLD_SERIAL_NUM>2018071014192880706100000002</OLD_SERIAL_NUM><HOSP_PATIENT_ID>0006046962</HOSP_PATIENT_ID><NAME>陆如玲</NAME><CERT_NO>460027197308120680</CERT_NO></ACCOUNT_LIST><ACCOUNT_LIST><ORDER_ID>201807102908733833</ORDER_ID><HOSP_ORDER_ID>WY201807102908733833</HOSP_ORDER_ID><ORDER_TYPE>1</ORDER_TYPE><AUDIT_STATUS>2</AUDIT_STATUS><HOSP_TRADE_ID>9718299</HOSP_TRADE_ID><PAY_CHANNEL_ID>1</PAY_CHANNEL_ID><SERIAL_NUM>2018071020340704406000000005</SERIAL_NUM><PAY_FEE>1530</PAY_FEE><PAY_DATETIME>2018-07-10 20:34:14</PAY_DATETIME><HOSP_PATIENT_ID>0006014356</HOSP_PATIENT_ID><NAME>刘洪菊</NAME><CERT_NO>46002419630507788X</CERT_NO></ACCOUNT_LIST><ACCOUNT_LIST><ORDER_ID>201807102908704213</ORDER_ID><HOSP_ORDER_ID>WY201807102908704213</HOSP_ORDER_ID><ORDER_TYPE>1</ORDER_TYPE><AUDIT_STATUS>2</AUDIT_STATUS><HOSP_TRADE_ID>9718289</HOSP_TRADE_ID><PAY_CHANNEL_ID>1</PAY_CHANNEL_ID><SERIAL_NUM>2018071020303566106100000017</SERIAL_NUM><PAY_FEE>1530</PAY_FEE><PAY_DATETIME>2018-07-10 20:30:43</PAY_DATETIME><HOSP_PATIENT_ID>T000354757</HOSP_PATIENT_ID><NAME>赵丹婷</NAME><CERT_NO>460006199003307820</CERT_NO></ACCOUNT_LIST><ACCOUNT_LIST><ORDER_ID>201807102908684870</ORDER_ID><HOSP_ORDER_ID>WY201807102908684870</HOSP_ORDER_ID><ORDER_TYPE>1</ORDER_TYPE><AUDIT_STATUS>2</AUDIT_STATUS><HOSP_TRADE_ID>9718285</HOSP_TRADE_ID><PAY_CHANNEL_ID>2</PAY_CHANNEL_ID><SERIAL_NUM>2018071020270127306100000001</SERIAL_NUM><PAY_FEE>1930</PAY_FEE><PAY_DATETIME>2018-07-10 20:29:01</PAY_DATETIME><HOSP_PATIENT_ID>0006049041</HOSP_PATIENT_ID><NAME>钟吉艳</NAME><CERT_NO>420625197510124426</CERT_NO></ACCOUNT_LIST><ACCOUNT_LIST><ORDER_ID>201807102908658077</ORDER_ID><HOSP_ORDER_ID>WY201807102908658077</HOSP_ORDER_ID><ORDER_TYPE>1</ORDER_TYPE><AUDIT_STATUS>2</AUDIT_STATUS><HOSP_TRADE_ID>9718270</HOSP_TRADE_ID><PAY_CHANNEL_ID>1</PAY_CHANNEL_ID><SERIAL_NUM>2018071020204500806100000007</SERIAL_NUM><PAY_FEE>1930</PAY_FEE><PAY_DATETIME>2018-07-10 20:20:55</PAY_DATETIME><HOSP_PATIENT_ID>0006049040</HOSP_PATIENT_ID><NAME>胡斌</NAME><CERT_NO>460025198310170910</CERT_NO></ACCOUNT_LIST><ACCOUNT_LIST><ORDER_ID>201807092898874062</ORDER_ID><HOSP_ORDER_ID>WY201807092898874062</HOSP_ORDER_ID><ORDER_TYPE>2</ORDER_TYPE><AUDIT_STATUS>2</AUDIT_STATUS><HOSP_TRADE_ID>573064@0006045569</HOSP_TRADE_ID><PAY_CHANNEL_ID>1</PAY_CHANNEL_ID><SERIAL_NUM>7457908</SERIAL_NUM><PAY_FEE>1930</PAY_FEE><PAY_DATETIME>2018-07-10 20:02:52</PAY_DATETIME><OLD_HOSP_TRADE_ID>9711944</OLD_HOSP_TRADE_ID><OLD_SERIAL_NUM>2018070916510270206000000002</OLD_SERIAL_NUM><HOSP_PATIENT_ID>0006045569</HOSP_PATIENT_ID><NAME>林柏霖</NAME><CERT_NO>469024201711060815</CERT_NO></ACCOUNT_LIST><ACCOUNT_LIST><ORDER_ID>201807102908524541</ORDER_ID><HOSP_ORDER_ID>WY201807102908524541</HOSP_ORDER_ID><ORDER_TYPE>1</ORDER_TYPE><AUDIT_STATUS>2</AUDIT_STATUS><HOSP_TRADE_ID>9718221</HOSP_TRADE_ID><PAY_CHANNEL_ID>2</PAY_CHANNEL_ID><SERIAL_NUM>2018071019571238306000000003</SERIAL_NUM><PAY_FEE>1930</PAY_FEE><PAY_DATETIME>2018-07-10 19:57:28</PAY_DATETIME><HOSP_PATIENT_ID>0005765762</HOSP_PATIENT_ID><NAME>雷健东</NAME><CERT_NO>440781199107258714</CERT_NO></ACCOUNT_LIST><ACCOUNT_LIST><ORDER_ID>201807102903178209</ORDER_ID><HOSP_ORDER_ID>WY201807102903178209</HOSP_ORDER_ID><ORDER_TYPE>2</ORDER_TYPE><AUDIT_STATUS>2</AUDIT_STATUS><HOSP_TRADE_ID>575660@0005982336</HOSP_TRADE_ID><PAY_CHANNEL_ID>1</PAY_CHANNEL_ID><SERIAL_NUM>7465254</SERIAL_NUM><PAY_FEE>1930</PAY_FEE><PAY_DATETIME>2018-07-10 19:56:40</PAY_DATETIME><OLD_HOSP_TRADE_ID>9715219</OLD_HOSP_TRADE_ID><OLD_SERIAL_NUM>2018071009554616306100000006</OLD_SERIAL_NUM><HOSP_PATIENT_ID>0005982336</HOSP_PATIENT_ID><NAME>周雪心</NAME><CERT_NO>460022198712260725</CERT_NO></ACCOUNT_LIST><ACCOUNT_LIST><ORDER_ID>201807102908482876</ORDER_ID><HOSP_ORDER_ID>WY201807102908482876</HOSP_ORDER_ID><ORDER_TYPE>1</ORDER_TYPE><AUDIT_STATUS>2</AUDIT_STATUS><HOSP_TRADE_ID>9718214</HOSP_TRADE_ID><PAY_CHANNEL_ID>1</PAY_CHANNEL_ID><SERIAL_NUM>2018071019523435006000000005</SERIAL_NUM><PAY_FEE>1930</PAY_FEE><PAY_DATETIME>2018-07-10 19:52:55</PAY_DATETIME><HOSP_PATIENT_ID>0006049061</HOSP_PATIENT_ID><NAME>高祥浩</NAME><CERT_NO>469025201606270016</CERT_NO></ACCOUNT_LIST><ACCOUNT_LIST><ORDER_ID>201807102908321817</ORDER_ID><HOSP_ORDER_ID>WY201807102908321817</HOSP_ORDER_ID><ORDER_TYPE>1</ORDER_TYPE><AUDIT_STATUS>2</AUDIT_STATUS><HOSP_TRADE_ID>9718174</HOSP_TRADE_ID><PAY_CHANNEL_ID>1</PAY_CHANNEL_ID><SERIAL_NUM>2018071019224573506000000006</SERIAL_NUM><PAY_FEE>1330</PAY_FEE><PAY_DATETIME>2018-07-10 19:22:54</PAY_DATETIME><HOSP_PATIENT_ID>0005823209</HOSP_PATIENT_ID><NAME>陈里阳</NAME><CERT_NO>460034199209050018</CERT_NO></ACCOUNT_LIST><ACCOUNT_LIST><ORDER_ID>201807102908327135</ORDER_ID><HOSP_ORDER_ID>WY201807102908327135</HOSP_ORDER_ID><ORDER_TYPE>1</ORDER_TYPE><AUDIT_STATUS>2</AUDIT_STATUS><HOSP_TRADE_ID>9718172</HOSP_TRADE_ID><PAY_CHANNEL_ID>2</PAY_CHANNEL_ID><SERIAL_NUM>2018071019213204006100000003</SERIAL_NUM><PAY_FEE>1330</PAY_FEE><PAY_DATETIME>2018-07-10 19:21:37</PAY_DATETIME><HOSP_PATIENT_ID>T000134621</HOSP_PATIENT_ID><NAME>黄秀容</NAME><CERT_NO>460100195306110020</CERT_NO></ACCOUNT_LIST><ACCOUNT_LIST><ORDER_ID>201807102903986860</ORDER_ID><HOSP_ORDER_ID>WY201807102903986860</HOSP_ORDER_ID><ORDER_TYPE>2</ORDER_TYPE><AUDIT_STATUS>2</AUDIT_STATUS><PAY_CHANNEL_ID>2</PAY_CHANNEL_ID><SERIAL_NUM>7466516</SERIAL_NUM><PAY_FEE>1930</PAY_FEE><PAY_DATETIME>2018-07-10 18:14:49</PAY_DATETIME><OLD_HOSP_TRADE_ID>9716218</OLD_HOSP_TRADE_ID><OLD_SERIAL_NUM>2018071011404170806000000004</OLD_SERIAL_NUM><HOSP_PATIENT_ID>0005254884</HOSP_PATIENT_ID><NAME>徐思杰</NAME><CERT_NO>430321198104140556</CERT_NO></ACCOUNT_LIST><ACCOUNT_LIST><ORDER_ID>201807102906414410</ORDER_ID><HOSP_ORDER_ID>WY201807102906414410</HOSP_ORDER_ID><ORDER_TYPE>1</ORDER_TYPE><AUDIT_STATUS>2</AUDIT_STATUS><HOSP_TRADE_ID>9718055</HOSP_TRADE_ID><PAY_CHANNEL_ID>1</PAY_CHANNEL_ID><SERIAL_NUM>2018071018140175100800000001</SERIAL_NUM><PAY_FEE>1330</PAY_FEE><PAY_DATETIME>2018-07-10 18:14:14</PAY_DATETIME><HOSP_PATIENT_ID>0001766310</HOSP_PATIENT_ID><NAME>吉月英</NAME><CERT_NO>460007198206125041</CERT_NO></ACCOUNT_LIST><ACCOUNT_LIST><ORDER_ID>201807102907814355</ORDER_ID><HOSP_ORDER_ID>WY201807102907814355</HOSP_ORDER_ID><ORDER_TYPE>1</ORDER_TYPE><AUDIT_STATUS>2</AUDIT_STATUS><HOSP_TRADE_ID>9718053</HOSP_TRADE_ID><PAY_CHANNEL_ID>2</PAY_CHANNEL_ID><SERIAL_NUM>2018071018134700006000000006</SERIAL_NUM><PAY_FEE>1930</PAY_FEE><PAY_DATETIME>2018-07-10 18:13:56</PAY_DATETIME><HOSP_PATIENT_ID>0006048996</HOSP_PATIENT_ID><NAME>杨静</NAME><CERT_NO>430522198610251440</CERT_NO></ACCOUNT_LIST><ACCOUNT_LIST><ORDER_ID>201807102907702173</ORDER_ID><HOSP_ORDER_ID>WY201807102907702173</HOSP_ORDER_ID><ORDER_TYPE>1</ORDER_TYPE><AUDIT_STATUS>2</AUDIT_STATUS><HOSP_TRADE_ID>9718052</HOSP_TRADE_ID><PAY_CHANNEL_ID>1</PAY_CHANNEL_ID><SERIAL_NUM>2018071018131507006100000001</SERIAL_NUM><PAY_FEE>1930</PAY_FEE><PAY_DATETIME>2018-07-10 18:13:25</PAY_DATETIME><HOSP_PATIENT_ID>0005816200</HOSP_PATIENT_ID><NAME>陈伟翔</NAME><CERT_NO>46902420140330083X</CERT_NO></ACCOUNT_LIST><ACCOUNT_LIST><ORDER_ID>201807102907589051</ORDER_ID><HOSP_ORDER_ID>WY201807102907589051</HOSP_ORDER_ID><ORDER_TYPE>1</ORDER_TYPE><AUDIT_STATUS>2</AUDIT_STATUS><HOSP_TRADE_ID>9718046</HOSP_TRADE_ID><PAY_CHANNEL_ID>1</PAY_CHANNEL_ID><SERIAL_NUM>2018071018093073606000000003</SERIAL_NUM><PAY_FEE>1930</PAY_FEE><PAY_DATETIME>2018-07-10 18:09:38</PAY_DATETIME><HOSP_PATIENT_ID>0005634769</HOSP_PATIENT_ID><NAME>马静妤</NAME><CERT_NO>469023201105185320</CERT_NO></ACCOUNT_LIST><ACCOUNT_LIST><ORDER_ID>201807102906524350</ORDER_ID><HOSP_ORDER_ID>WY201807102906524350</HOSP_ORDER_ID><ORDER_TYPE>2</ORDER_TYPE><AUDIT_STATUS>2</AUDIT_STATUS><PAY_CHANNEL_ID>11</PAY_CHANNEL_ID><SERIAL_NUM>7472176</SERIAL_NUM><PAY_FEE>1530</PAY_FEE><PAY_DATETIME>2018-07-10 18:08:26</PAY_DATETIME><OLD_SERIAL_NUM>2018071018081114900900000001</OLD_SERIAL_NUM><HOSP_PATIENT_ID>0001766310</HOSP_PATIENT_ID><NAME>吉月英</NAME><CERT_NO>460007198206125041</CERT_NO></ACCOUNT_LIST><ACCOUNT_LIST><ORDER_ID>201807102906524350</ORDER_ID><HOSP_ORDER_ID>WY201807102906524350</HOSP_ORDER_ID><ORDER_TYPE>1</ORDER_TYPE><AUDIT_STATUS>2</AUDIT_STATUS><PAY_CHANNEL_ID>11</PAY_CHANNEL_ID><SERIAL_NUM>2018071018081114900900000001</SERIAL_NUM><PAY_FEE>1530</PAY_FEE><PAY_DATETIME>2018-07-10 18:08:23</PAY_DATETIME><HOSP_PATIENT_ID>0001766310</HOSP_PATIENT_ID><NAME>吉月英</NAME><CERT_NO>460007198206125041</CERT_NO></ACCOUNT_LIST><ACCOUNT_LIST><ORDER_ID>201807102903683665</ORDER_ID><HOSP_ORDER_ID>WY201807102903683665</HOSP_ORDER_ID><ORDER_TYPE>2</ORDER_TYPE><AUDIT_STATUS>2</AUDIT_STATUS><HOSP_TRADE_ID>573475@0005634769</HOSP_TRADE_ID><PAY_CHANNEL_ID>1</PAY_CHANNEL_ID><SERIAL_NUM>7466043</SERIAL_NUM><PAY_FEE>1930</PAY_FEE><PAY_DATETIME>2018-07-10 18:07:47</PAY_DATETIME><OLD_HOSP_TRADE_ID>9715966</OLD_HOSP_TRADE_ID><OLD_SERIAL_NUM>2018071011034575406100000009</OLD_SERIAL_NUM><HOSP_PATIENT_ID>0005634769</HOSP_PATIENT_ID><NAME>马静妤</NAME><CERT_NO>469023201105185320</CERT_NO></ACCOUNT_LIST><ACCOUNT_LIST><ORDER_ID>201807102906520023</ORDER_ID><HOSP_ORDER_ID>WY201807102906520023</HOSP_ORDER_ID><ORDER_TYPE>2</ORDER_TYPE><AUDIT_STATUS>2</AUDIT_STATUS><PAY_CHANNEL_ID>11</PAY_CHANNEL_ID><SERIAL_NUM>7472030</SERIAL_NUM><PAY_FEE>1530</PAY_FEE><PAY_DATETIME>2018-07-10 17:56:08</PAY_DATETIME><OLD_SERIAL_NUM>2018071017554011200900000002</OLD_SERIAL_NUM><HOSP_PATIENT_ID>0001766310</HOSP_PATIENT_ID><NAME>吉月英</NAME><CERT_NO>460007198206125041</CERT_NO></ACCOUNT_LIST><ACCOUNT_LIST><ORDER_ID>201807102906520023</ORDER_ID><HOSP_ORDER_ID>WY201807102906520023</HOSP_ORDER_ID><ORDER_TYPE>1</ORDER_TYPE><AUDIT_STATUS>2</AUDIT_STATUS><PAY_CHANNEL_ID>11</PAY_CHANNEL_ID><SERIAL_NUM>2018071017554011200900000002</SERIAL_NUM><PAY_FEE>1530</PAY_FEE><PAY_DATETIME>2018-07-10 17:56:03</PAY_DATETIME><HOSP_PATIENT_ID>0001766310</HOSP_PATIENT_ID><NAME>吉月英</NAME><CERT_NO>460007198206125041</CERT_NO></ACCOUNT_LIST><ACCOUNT_LIST><ORDER_ID>201807102907191162</ORDER_ID><HOSP_ORDER_ID>WY201807102907191162</HOSP_ORDER_ID><ORDER_TYPE>1</ORDER_TYPE><AUDIT_STATUS>2</AUDIT_STATUS><HOSP_TRADE_ID>9717991</HOSP_TRADE_ID><PAY_CHANNEL_ID>2</PAY_CHANNEL_ID><SERIAL_NUM>2018071017385033406000000005</SERIAL_NUM><PAY_FEE>1930</PAY_FEE><PAY_DATETIME>2018-07-10 17:38:57</PAY_DATETIME><HOSP_PATIENT_ID>0006048119</HOSP_PATIENT_ID><NAME>梁振文</NAME><CERT_NO>460007199002100015</CERT_NO></ACCOUNT_LIST><ACCOUNT_LIST><ORDER_ID>201807102907303180</ORDER_ID><HOSP_ORDER_ID>WY201807102907303180</HOSP_ORDER_ID><ORDER_TYPE>1</ORDER_TYPE><AUDIT_STATUS>2</AUDIT_STATUS><HOSP_TRADE_ID>9717985</HOSP_TRADE_ID><PAY_CHANNEL_ID>1</PAY_CHANNEL_ID><SERIAL_NUM>2018071017360237606000000002</SERIAL_NUM><PAY_FEE>1330</PAY_FEE><PAY_DATETIME>2018-07-10 17:36:08</PAY_DATETIME><HOSP_PATIENT_ID>0006048955</HOSP_PATIENT_ID><NAME>符芳燕</NAME><CERT_NO>460028199509213264</CERT_NO></ACCOUNT_LIST><ACCOUNT_LIST><ORDER_ID>201807102907161134</ORDER_ID><HOSP_ORDER_ID>WY201807102907161134</HOSP_ORDER_ID><ORDER_TYPE>1</ORDER_TYPE><AUDIT_STATUS>2</AUDIT_STATUS><HOSP_TRADE_ID>9717858</HOSP_TRADE_ID><PAY_CHANNEL_ID>1</PAY_CHANNEL_ID><SERIAL_NUM>2018071017005391106100000021</SERIAL_NUM><PAY_FEE>1930</PAY_FEE><PAY_DATETIME>2018-07-10 17:01:11</PAY_DATETIME><HOSP_PATIENT_ID>0005301360</HOSP_PATIENT_ID><NAME>曾昌荣</NAME><CERT_NO>460100196611031868</CERT_NO></ACCOUNT_LIST><ACCOUNT_LIST><ORDER_ID>201807102906930754</ORDER_ID><HOSP_ORDER_ID>WY201807102906930754</HOSP_ORDER_ID><ORDER_TYPE>1</ORDER_TYPE><AUDIT_STATUS>2</AUDIT_STATUS><HOSP_TRADE_ID>9717836</HOSP_TRADE_ID><PAY_CHANNEL_ID>1</PAY_CHANNEL_ID><SERIAL_NUM>2018071016561403506000000002</SERIAL_NUM><PAY_FEE>1930</PAY_FEE><PAY_DATETIME>2018-07-10 16:56:25</PAY_DATETIME><HOSP_PATIENT_ID>0006030268</HOSP_PATIENT_ID><NAME>吴相怡</NAME><CERT_NO>460031198212130023</CERT_NO></ACCOUNT_LIST><ACCOUNT_LIST><ORDER_ID>201807102907037555</ORDER_ID><HOSP_ORDER_ID>WY201807102907037555</HOSP_ORDER_ID><ORDER_TYPE>1</ORDER_TYPE><AUDIT_STATUS>2</AUDIT_STATUS><HOSP_TRADE_ID>9717824</HOSP_TRADE_ID><PAY_CHANNEL_ID>1</PAY_CHANNEL_ID><SERIAL_NUM>2018071016543575506100000005</SERIAL_NUM><PAY_FEE>1530</PAY_FEE><PAY_DATETIME>2018-07-10 16:54:45</PAY_DATETIME><HOSP_PATIENT_ID>0006048901</HOSP_PATIENT_ID><NAME>王成凯</NAME><CERT_NO>460027199107206639</CERT_NO></ACCOUNT_LIST><ACCOUNT_LIST><ORDER_ID>201807102906499668</ORDER_ID><HOSP_ORDER_ID>WY201807102906499668</HOSP_ORDER_ID><ORDER_TYPE>1</ORDER_TYPE><AUDIT_STATUS>2</AUDIT_STATUS><HOSP_TRADE_ID>9717698</HOSP_TRADE_ID><PAY_CHANNEL_ID>1</PAY_CHANNEL_ID><SERIAL_NUM>2018071016290580900900000001</SERIAL_NUM><PAY_FEE>1930</PAY_FEE><PAY_DATETIME>2018-07-10 16:29:19</PAY_DATETIME><HOSP_PATIENT_ID>0005901781</HOSP_PATIENT_ID><NAME>林政</NAME><CERT_NO>460003199508126671</CERT_NO></ACCOUNT_LIST><ACCOUNT_LIST><ORDER_ID>201807102905563656</ORDER_ID><HOSP_ORDER_ID>WY201807102905563656</HOSP_ORDER_ID><ORDER_TYPE>1</ORDER_TYPE><AUDIT_STATUS>2</AUDIT_STATUS><HOSP_TRADE_ID>9717556</HOSP_TRADE_ID><PAY_CHANNEL_ID>1</PAY_CHANNEL_ID><SERIAL_NUM>2018071016091916806000000002</SERIAL_NUM><PAY_FEE>1330</PAY_FEE><PAY_DATETIME>2018-07-10 16:09:30</PAY_DATETIME><HOSP_PATIENT_ID>0006048728</HOSP_PATIENT_ID><NAME>牛帝安</NAME><CERT_NO>460003200205164211</CERT_NO></ACCOUNT_LIST><ACCOUNT_LIST><ORDER_ID>201807102905534782</ORDER_ID><HOSP_ORDER_ID>WY201807102905534782</HOSP_ORDER_ID><ORDER_TYPE>1</ORDER_TYPE><AUDIT_STATUS>2</AUDIT_STATUS><HOSP_TRADE_ID>9717531</HOSP_TRADE_ID><PAY_CHANNEL_ID>2</PAY_CHANNEL_ID><SERIAL_NUM>2018071016060951006000000002</SERIAL_NUM><PAY_FEE>1930</PAY_FEE><PAY_DATETIME>2018-07-10 16:06:19</PAY_DATETIME><HOSP_PATIENT_ID>0006023034</HOSP_PATIENT_ID><NAME>文光武</NAME><CERT_NO>460006195010202316</CERT_NO></ACCOUNT_LIST><ACCOUNT_LIST><ORDER_ID>201807102905469171</ORDER_ID><HOSP_ORDER_ID>WY201807102905469171</HOSP_ORDER_ID><ORDER_TYPE>1</ORDER_TYPE><AUDIT_STATUS>2</AUDIT_STATUS><HOSP_TRADE_ID>9717458</HOSP_TRADE_ID><PAY_CHANNEL_ID>2</PAY_CHANNEL_ID><SERIAL_NUM>2018071015554232006100000005</SERIAL_NUM><PAY_FEE>1930</PAY_FEE><PAY_DATETIME>2018-07-10 15:56:36</PAY_DATETIME><HOSP_PATIENT_ID>0006048558</HOSP_PATIENT_ID><NAME>周光海</NAME><CERT_NO>460029197602022654</CERT_NO></ACCOUNT_LIST><ACCOUNT_LIST><ORDER_ID>201807102905358842</ORDER_ID><HOSP_ORDER_ID>WY201807102905358842</HOSP_ORDER_ID><ORDER_TYPE>1</ORDER_TYPE><AUDIT_STATUS>2</AUDIT_STATUS><HOSP_TRADE_ID>9717347</HOSP_TRADE_ID><PAY_CHANNEL_ID>2</PAY_CHANNEL_ID><SERIAL_NUM>2018071015375798606000000006</SERIAL_NUM><PAY_FEE>1930</PAY_FEE><PAY_DATETIME>2018-07-10 15:38:06</PAY_DATETIME><HOSP_PATIENT_ID>0001748511</HOSP_PATIENT_ID><NAME>孔秋婷</NAME><CERT_NO>460105200907166623</CERT_NO></ACCOUNT_LIST><ACCOUNT_LIST><ORDER_ID>201807102905311164</ORDER_ID><HOSP_ORDER_ID>WY201807102905311164</HOSP_ORDER_ID><ORDER_TYPE>1</ORDER_TYPE><AUDIT_STATUS>2</AUDIT_STATUS><HOSP_TRADE_ID>9717257</HOSP_TRADE_ID><PAY_CHANNEL_ID>2</PAY_CHANNEL_ID><SERIAL_NUM>2018071015260954006000000003</SERIAL_NUM><PAY_FEE>1930</PAY_FEE><PAY_DATETIME>2018-07-10 15:26:28</PAY_DATETIME><HOSP_PATIENT_ID>0006048583</HOSP_PATIENT_ID><NAME>羊志强</NAME><CERT_NO>460003199210137810</CERT_NO></ACCOUNT_LIST><ACCOUNT_LIST><ORDER_ID>201807102905018157</ORDER_ID><HOSP_ORDER_ID>WY201807102905018157</HOSP_ORDER_ID><ORDER_TYPE>1</ORDER_TYPE><AUDIT_STATUS>2</AUDIT_STATUS><HOSP_TRADE_ID>9716973</HOSP_TRADE_ID><PAY_CHANNEL_ID>1</PAY_CHANNEL_ID><SERIAL_NUM>2018071014490018606100000001</SERIAL_NUM><PAY_FEE>1930</PAY_FEE><PAY_DATETIME>2018-07-10 14:49:16</PAY_DATETIME><HOSP_PATIENT_ID>0005294621</HOSP_PATIENT_ID><NAME>庞群参</NAME><CERT_NO>110108197009115749</CERT_NO></ACCOUNT_LIST><ACCOUNT_LIST><ORDER_ID>201807102904877034</ORDER_ID><HOSP_ORDER_ID>WY201807102904877034</HOSP_ORDER_ID><ORDER_TYPE>1</ORDER_TYPE><AUDIT_STATUS>2</AUDIT_STATUS><HOSP_TRADE_ID>9716750</HOSP_TRADE_ID><PAY_CHANNEL_ID>2</PAY_CHANNEL_ID><SERIAL_NUM>2018071014240335906000000001</SERIAL_NUM><PAY_FEE>1930</PAY_FEE><PAY_DATETIME>2018-07-10 14:24:10</PAY_DATETIME><HOSP_PATIENT_ID>0006048165</HOSP_PATIENT_ID><NAME>杨香潮</NAME><CERT_NO>460022199112084822</CERT_NO></ACCOUNT_LIST><ACCOUNT_LIST><ORDER_ID>201807102904853660</ORDER_ID><HOSP_ORDER_ID>WY201807102904853660</HOSP_ORDER_ID><ORDER_TYPE>1</ORDER_TYPE><AUDIT_STATUS>2</AUDIT_STATUS><HOSP_TRADE_ID>9716721</HOSP_TRADE_ID><PAY_CHANNEL_ID>1</PAY_CHANNEL_ID><SERIAL_NUM>2018071014193963806100000005</SERIAL_NUM><PAY_FEE>1930</PAY_FEE><PAY_DATETIME>2018-07-10 14:20:00</PAY_DATETIME><HOSP_PATIENT_ID>0006048171</HOSP_PATIENT_ID><NAME>王吉松</NAME><CERT_NO>460028198010156411</CERT_NO></ACCOUNT_LIST><ACCOUNT_LIST><ORDER_ID>201807102904939390</ORDER_ID><HOSP_ORDER_ID>WY201807102904939390</HOSP_ORDER_ID><ORDER_TYPE>1</ORDER_TYPE><AUDIT_STATUS>2</AUDIT_STATUS><HOSP_TRADE_ID>9716719</HOSP_TRADE_ID><PAY_CHANNEL_ID>1</PAY_CHANNEL_ID><SERIAL_NUM>2018071014192880706100000002</SERIAL_NUM><PAY_FEE>1530</PAY_FEE><PAY_DATETIME>2018-07-10 14:19:37</PAY_DATETIME><HOSP_PATIENT_ID>0006046962</HOSP_PATIENT_ID><NAME>陆如玲</NAME><CERT_NO>460027197308120680</CERT_NO></ACCOUNT_LIST><ACCOUNT_LIST><ORDER_ID>201807102904728323</ORDER_ID><HOSP_ORDER_ID>WY201807102904728323</HOSP_ORDER_ID><ORDER_TYPE>1</ORDER_TYPE><AUDIT_STATUS>2</AUDIT_STATUS><HOSP_TRADE_ID>9716535</HOSP_TRADE_ID><PAY_CHANNEL_ID>1</PAY_CHANNEL_ID><SERIAL_NUM>2018071013542435906000000002</SERIAL_NUM><PAY_FEE>1930</PAY_FEE><PAY_DATETIME>2018-07-10 13:54:32</PAY_DATETIME><HOSP_PATIENT_ID>0004845257</HOSP_PATIENT_ID><NAME>黄夏雨</NAME><CERT_NO>46000219810403522X</CERT_NO></ACCOUNT_LIST><ACCOUNT_LIST><ORDER_ID>201807102903173575</ORDER_ID><HOSP_ORDER_ID>WY201807102903173575</HOSP_ORDER_ID><ORDER_TYPE>1</ORDER_TYPE><AUDIT_STATUS>2</AUDIT_STATUS><HOSP_TRADE_ID>9716454</HOSP_TRADE_ID><PAY_CHANNEL_ID>1</PAY_CHANNEL_ID><SERIAL_NUM>2018071013074958400900000003</SERIAL_NUM><PAY_FEE>1930</PAY_FEE><PAY_DATETIME>2018-07-10 13:08:13</PAY_DATETIME><HOSP_PATIENT_ID>0004358270</HOSP_PATIENT_ID><NAME>蔡仁安</NAME><CERT_NO>460004198707181413</CERT_NO></ACCOUNT_LIST><ACCOUNT_LIST><ORDER_ID>201807102904433194</ORDER_ID><HOSP_ORDER_ID>WY201807102904433194</HOSP_ORDER_ID><ORDER_TYPE>1</ORDER_TYPE><AUDIT_STATUS>2</AUDIT_STATUS><HOSP_TRADE_ID>9716439</HOSP_TRADE_ID><PAY_CHANNEL_ID>2</PAY_CHANNEL_ID><SERIAL_NUM>2018071013003538806000000022</SERIAL_NUM><PAY_FEE>1530</PAY_FEE><PAY_DATETIME>2018-07-10 13:00:40</PAY_DATETIME><HOSP_PATIENT_ID>0005248864</HOSP_PATIENT_ID><NAME>宋翠莲</NAME><CERT_NO>431026199105312525</CERT_NO></ACCOUNT_LIST><ACCOUNT_LIST><ORDER_ID>201807102904397465</ORDER_ID><HOSP_ORDER_ID>WY201807102904397465</HOSP_ORDER_ID><ORDER_TYPE>1</ORDER_TYPE><AUDIT_STATUS>2</AUDIT_STATUS><HOSP_TRADE_ID>9716425</HOSP_TRADE_ID><PAY_CHANNEL_ID>1</PAY_CHANNEL_ID><SERIAL_NUM>2018071012524375206000000003</SERIAL_NUM><PAY_FEE>1530</PAY_FEE><PAY_DATETIME>2018-07-10 12:52:51</PAY_DATETIME><HOSP_PATIENT_ID>0005099697</HOSP_PATIENT_ID><NAME>杨婷</NAME><CERT_NO>460103199410051523</CERT_NO></ACCOUNT_LIST><ACCOUNT_LIST><ORDER_ID>201807102904391730</ORDER_ID><HOSP_ORDER_ID>WY201807102904391730</HOSP_ORDER_ID><ORDER_TYPE>1</ORDER_TYPE><AUDIT_STATUS>2</AUDIT_STATUS><HOSP_TRADE_ID>9716419</HOSP_TRADE_ID><PAY_CHANNEL_ID>1</PAY_CHANNEL_ID><SERIAL_NUM>2018071012521090406100000002</SERIAL_NUM><PAY_FEE>1330</PAY_FEE><PAY_DATETIME>2018-07-10 12:52:20</PAY_DATETIME><HOSP_PATIENT_ID>0005806311</HOSP_PATIENT_ID><NAME>肖容容</NAME><CERT_NO>441802198906163021</CERT_NO></ACCOUNT_LIST><ACCOUNT_LIST><ORDER_ID>201807102904097317</ORDER_ID><HOSP_ORDER_ID>WY201807102904097317</HOSP_ORDER_ID><ORDER_TYPE>1</ORDER_TYPE><AUDIT_STATUS>2</AUDIT_STATUS><HOSP_TRADE_ID>9716266</HOSP_TRADE_ID><PAY_CHANNEL_ID>1</PAY_CHANNEL_ID><SERIAL_NUM>2018071011543490706000000002</SERIAL_NUM><PAY_FEE>1930</PAY_FEE><PAY_DATETIME>2018-07-10 11:54:45</PAY_DATETIME><HOSP_PATIENT_ID>0006027942</HOSP_PATIENT_ID><NAME>羊初庆</NAME><CERT_NO>460003198709066682</CERT_NO></ACCOUNT_LIST><ACCOUNT_LIST><ORDER_ID>201807102903986860</ORDER_ID><HOSP_ORDER_ID>WY201807102903986860</HOSP_ORDER_ID><ORDER_TYPE>1</ORDER_TYPE><AUDIT_STATUS>2</AUDIT_STATUS><HOSP_TRADE_ID>9716218</HOSP_TRADE_ID><PAY_CHANNEL_ID>2</PAY_CHANNEL_ID><SERIAL_NUM>2018071011404170806000000004</SERIAL_NUM><PAY_FEE>1930</PAY_FEE><PAY_DATETIME>2018-07-10 11:40:47</PAY_DATETIME><HOSP_PATIENT_ID>0005254884</HOSP_PATIENT_ID><NAME>徐思杰</NAME><CERT_NO>430321198104140556</CERT_NO></ACCOUNT_LIST><ACCOUNT_LIST><ORDER_ID>201807102903692800</ORDER_ID><HOSP_ORDER_ID>WY201807102903692800</HOSP_ORDER_ID><ORDER_TYPE>1</ORDER_TYPE><AUDIT_STATUS>2</AUDIT_STATUS><HOSP_TRADE_ID>9715990</HOSP_TRADE_ID><PAY_CHANNEL_ID>1</PAY_CHANNEL_ID><SERIAL_NUM>2018071011044208806100000005</SERIAL_NUM><PAY_FEE>1330</PAY_FEE><PAY_DATETIME>2018-07-10 11:07:28</PAY_DATETIME><HOSP_PATIENT_ID>0001704285</HOSP_PATIENT_ID><NAME>符景娇</NAME><CERT_NO>460002197705100029</CERT_NO></ACCOUNT_LIST><ACCOUNT_LIST><ORDER_ID>201807102903683665</ORDER_ID><HOSP_ORDER_ID>WY201807102903683665</HOSP_ORDER_ID><ORDER_TYPE>1</ORDER_TYPE><AUDIT_STATUS>2</AUDIT_STATUS><HOSP_TRADE_ID>9715966</HOSP_TRADE_ID><PAY_CHANNEL_ID>1</PAY_CHANNEL_ID><SERIAL_NUM>2018071011034575406100000009</SERIAL_NUM><PAY_FEE>1930</PAY_FEE><PAY_DATETIME>2018-07-10 11:03:53</PAY_DATETIME><HOSP_PATIENT_ID>0005634769</HOSP_PATIENT_ID><NAME>马静妤</NAME><CERT_NO>469023201105185320</CERT_NO></ACCOUNT_LIST><ACCOUNT_LIST><ORDER_ID>201807102903609619</ORDER_ID><HOSP_ORDER_ID>WY201807102903609619</HOSP_ORDER_ID><ORDER_TYPE>1</ORDER_TYPE><AUDIT_STATUS>2</AUDIT_STATUS><HOSP_TRADE_ID>9715901</HOSP_TRADE_ID><PAY_CHANNEL_ID>2</PAY_CHANNEL_ID><SERIAL_NUM>2018071010524548406000000006</SERIAL_NUM><PAY_FEE>4130</PAY_FEE><PAY_DATETIME>2018-07-10 10:55:21</PAY_DATETIME><HOSP_PATIENT_ID>0005743962</HOSP_PATIENT_ID><NAME>陈世兴</NAME><CERT_NO>460100197009231511</CERT_NO></ACCOUNT_LIST><ACCOUNT_LIST><ORDER_ID>201807032855695109</ORDER_ID><HOSP_ORDER_ID>WY201807032855695109</HOSP_ORDER_ID><ORDER_TYPE>2</ORDER_TYPE><AUDIT_STATUS>2</AUDIT_STATUS><HOSP_TRADE_ID>573125@0005743962</HOSP_TRADE_ID><PAY_CHANNEL_ID>2</PAY_CHANNEL_ID><SERIAL_NUM>7389119</SERIAL_NUM><PAY_FEE>4130</PAY_FEE><PAY_DATETIME>2018-07-10 10:51:29</PAY_DATETIME><OLD_HOSP_TRADE_ID>9683609</OLD_HOSP_TRADE_ID><OLD_SERIAL_NUM>2018070312452376906000000004</OLD_SERIAL_NUM><HOSP_PATIENT_ID>0005743962</HOSP_PATIENT_ID><NAME>陈世兴</NAME><CERT_NO>460100197009231511</CERT_NO></ACCOUNT_LIST><ACCOUNT_LIST><ORDER_ID>201807102903502186</ORDER_ID><HOSP_ORDER_ID>WY201807102903502186</HOSP_ORDER_ID><ORDER_TYPE>1</ORDER_TYPE><AUDIT_STATUS>2</AUDIT_STATUS><HOSP_TRADE_ID>9715708</HOSP_TRADE_ID><PAY_CHANNEL_ID>1</PAY_CHANNEL_ID><SERIAL_NUM>2018071010360454506100000001</SERIAL_NUM><PAY_FEE>1530</PAY_FEE><PAY_DATETIME>2018-07-10 10:36:16</PAY_DATETIME><HOSP_PATIENT_ID>0006043013</HOSP_PATIENT_ID><NAME>蒋影</NAME><CERT_NO>341125198010180024</CERT_NO></ACCOUNT_LIST><ACCOUNT_LIST><ORDER_ID>201807102903357043</ORDER_ID><HOSP_ORDER_ID>WY201807102903357043</HOSP_ORDER_ID><ORDER_TYPE>1</ORDER_TYPE><AUDIT_STATUS>2</AUDIT_STATUS><HOSP_TRADE_ID>9715500</HOSP_TRADE_ID><PAY_CHANNEL_ID>1</PAY_CHANNEL_ID><SERIAL_NUM>2018071010181312106100000003</SERIAL_NUM><PAY_FEE>1930</PAY_FEE><PAY_DATETIME>2018-07-10 10:18:32</PAY_DATETIME><HOSP_PATIENT_ID>T000318872</HOSP_PATIENT_ID><NAME>王玉蝶</NAME><CERT_NO>460100196209201582</CERT_NO></ACCOUNT_LIST><ACCOUNT_LIST><ORDER_ID>201807102903178209</ORDER_ID><HOSP_ORDER_ID>WY201807102903178209</HOSP_ORDER_ID><ORDER_TYPE>1</ORDER_TYPE><AUDIT_STATUS>2</AUDIT_STATUS><HOSP_TRADE_ID>9715219</HOSP_TRADE_ID><PAY_CHANNEL_ID>1</PAY_CHANNEL_ID><SERIAL_NUM>2018071009554616306100000006</SERIAL_NUM><PAY_FEE>1930</PAY_FEE><PAY_DATETIME>2018-07-10 09:55:56</PAY_DATETIME><HOSP_PATIENT_ID>0005982336</HOSP_PATIENT_ID><NAME>周雪心</NAME><CERT_NO>460022198712260725</CERT_NO></ACCOUNT_LIST><ACCOUNT_LIST><ORDER_ID>201807102903124051</ORDER_ID><HOSP_ORDER_ID>WY201807102903124051</HOSP_ORDER_ID><ORDER_TYPE>1</ORDER_TYPE><AUDIT_STATUS>2</AUDIT_STATUS><HOSP_TRADE_ID>9715188</HOSP_TRADE_ID><PAY_CHANNEL_ID>1</PAY_CHANNEL_ID><SERIAL_NUM>2018071009531595606100000003</SERIAL_NUM><PAY_FEE>1930</PAY_FEE><PAY_DATETIME>2018-07-10 09:53:26</PAY_DATETIME><HOSP_PATIENT_ID>0006047300</HOSP_PATIENT_ID><NAME>郑洁</NAME><CERT_NO>469021201109112126</CERT_NO></ACCOUNT_LIST><ACCOUNT_LIST><ORDER_ID>201807102903076545</ORDER_ID><HOSP_ORDER_ID>WY201807102903076545</HOSP_ORDER_ID><ORDER_TYPE>1</ORDER_TYPE><AUDIT_STATUS>2</AUDIT_STATUS><HOSP_TRADE_ID>9714974</HOSP_TRADE_ID><PAY_CHANNEL_ID>1</PAY_CHANNEL_ID><SERIAL_NUM>2018071009380814406000000001</SERIAL_NUM><PAY_FEE>1930</PAY_FEE><PAY_DATETIME>2018-07-10 09:38:17</PAY_DATETIME><HOSP_PATIENT_ID>0005783095</HOSP_PATIENT_ID><NAME>陈海陆</NAME><CERT_NO>460001199202220320</CERT_NO></ACCOUNT_LIST><ACCOUNT_LIST><ORDER_ID>201807092900913558</ORDER_ID><HOSP_ORDER_ID>WY201807092900913558</HOSP_ORDER_ID><ORDER_TYPE>1</ORDER_TYPE><AUDIT_STATUS>2</AUDIT_STATUS><HOSP_TRADE_ID>9714283</HOSP_TRADE_ID><PAY_CHANNEL_ID>2</PAY_CHANNEL_ID><SERIAL_NUM>2018071008481994700800000002</SERIAL_NUM><PAY_FEE>1930</PAY_FEE><PAY_DATETIME>2018-07-10 08:48:28</PAY_DATETIME><HOSP_PATIENT_ID>0005386576</HOSP_PATIENT_ID><NAME>陈晓锋</NAME><CERT_NO>46010319890812211X</CERT_NO></ACCOUNT_LIST><ACCOUNT_LIST><ORDER_ID>201807102901945866</ORDER_ID><HOSP_ORDER_ID>WY201807102901945866</HOSP_ORDER_ID><ORDER_TYPE>1</ORDER_TYPE><AUDIT_STATUS>2</AUDIT_STATUS><HOSP_TRADE_ID>9713224</HOSP_TRADE_ID><PAY_CHANNEL_ID>1</PAY_CHANNEL_ID><SERIAL_NUM>2018071007251070706100000002</SERIAL_NUM><PAY_FEE>1930</PAY_FEE><PAY_DATETIME>2018-07-10 07:25:16</PAY_DATETIME><HOSP_PATIENT_ID>0006044396</HOSP_PATIENT_ID><NAME>李泓萱</NAME><CERT_NO>469007200902210045</CERT_NO></ACCOUNT_LIST><ACCOUNT_LIST><ORDER_ID>201807092901458488</ORDER_ID><HOSP_ORDER_ID>WY201807092901458488</HOSP_ORDER_ID><ORDER_TYPE>1</ORDER_TYPE><AUDIT_STATUS>2</AUDIT_STATUS><HOSP_TRADE_ID>9713022</HOSP_TRADE_ID><PAY_CHANNEL_ID>1</PAY_CHANNEL_ID><SERIAL_NUM>2018071000132792806100000001</SERIAL_NUM><PAY_FEE>1930</PAY_FEE><PAY_DATETIME>2018-07-10 00:13:40</PAY_DATETIME><HOSP_PATIENT_ID>0005909470</HOSP_PATIENT_ID><NAME>范高德</NAME><CERT_NO>460022198908082713</CERT_NO></ACCOUNT_LIST><ACCOUNT_LIST><ORDER_ID>201807092901442338</ORDER_ID><HOSP_ORDER_ID>WY201807092901442338</HOSP_ORDER_ID><ORDER_TYPE>1</ORDER_TYPE><AUDIT_STATUS>2</AUDIT_STATUS><HOSP_TRADE_ID>9713015</HOSP_TRADE_ID><PAY_CHANNEL_ID>2</PAY_CHANNEL_ID><SERIAL_NUM>2018071000074189506000000004</SERIAL_NUM><PAY_FEE>1930</PAY_FEE><PAY_DATETIME>2018-07-10 00:08:27</PAY_DATETIME><HOSP_PATIENT_ID>0006045923</HOSP_PATIENT_ID><NAME>陈升院</NAME><CERT_NO>520221198411162727</CERT_NO></ACCOUNT_LIST></RES></ROOT>
